LICENSE
MANIFEST.in
README.md
setup.py
codewerdz/__init__.py
codewerdz/git/__init__.py
codewerdz/git/cli.py
codewerdz/git/streaming_json_list_printer.py
codewerdz/git/log/__init__.py
codewerdz/git/log/git_log_parser.py
codewerdz/git/log/git_log_process.py
codewerdz/git/log/log_command.py
codewerdz/git/metrics/__init__.py
codewerdz/git/metrics/commit_analyzer.py
codewerdz/git/metrics/metrics_command.py
codewerdz/git/process/__init__.py
codewerdz/git/process/git_process.py
codewerdz/git/process/line_output_shell_process.py
codewerdz/git/tests/__init__.py
codewerdz/git/tests/test_cli.py
codewerdz_git.egg-info/PKG-INFO
codewerdz_git.egg-info/SOURCES.txt
codewerdz_git.egg-info/dependency_links.txt
codewerdz_git.egg-info/entry_points.txt
codewerdz_git.egg-info/not-zip-safe
codewerdz_git.egg-info/requires.txt
codewerdz_git.egg-info/top_level.txt