Metadata-Version: 1.1
Name: codewerdz-git
Version: 0.1
Summary: A tool that analyses git to determine the ratio of code commits to doc commits.
Home-page: https://github.com/codewerdz/codewerdz-git
Author: Troy Howard
Author-email: thoward37@gmail.com
License: MIT
Keywords: git documentation datascience analysis log
Platform: UNKNOWN
Classifier: Development Status :: 3 - Alpha
Classifier: License :: OSI Approved :: MIT License
Classifier: Programming Language :: Python :: 2.7
